smlight_cc_flasher/__init__.py
smlight_cc_flasher/__main__.py
smlight_cc_flasher/_version.py
smlight_cc_flasher/cli.py
smlight_cc_flasher/command.py
smlight_cc_flasher/const.py
smlight_cc_flasher/device.py
smlight_cc_flasher/exceptions.py
smlight_cc_flasher/firmware.py
smlight_cc_flasher/flasher.py
smlight_cc_flasher/gpio.py
smlight_cc_flasher/py.typed
smlight_cc_flasher-0.1.5.dist-info/METADATA
smlight_cc_flasher-0.1.5.dist-info/WHEEL
smlight_cc_flasher-0.1.5.dist-info/entry_points.txt
smlight_cc_flasher-0.1.5.dist-info/licenses/LICENSE
smlight_cc_flasher-0.1.5.dist-info/RECORD
