Metadata-Version: 2.4
Name: smlight-cc-flasher
Version: 0.1.5
Summary: Flasher for SMLIGHT CC26xx Devices
Author-email: Tim Lunn <tl@smlight.tech>, Jelmer Tiete <jelmer@tiete.be>
License:                                  Apache License
License-File: LICENSE
Classifier: Development Status :: 4 - Beta
Classifier: Environment :: Console
Classifier: Intended Audience :: End Users/Desktop
Classifier: License :: OSI Approved :: Apache Software License
Classifier: Operating System :: MacOS
Classifier: Operating System :: Microsoft :: Windows
Classifier: Operating System :: POSIX :: Linux
Classifier: Programming Language :: Python :: 3
Classifier: Topic :: Scientific/Engineering
Requires-Python: >=3.12
Requires-Dist: coloredlogs~=15.0
Requires-Dist: gpiod>=2.4.0
Requires-Dist: intelhex~=2.3.0
Requires-Dist: pyserial-asyncio~=0.6
Requires-Dist: pysmlight~=0.2.9
Requires-Dist: python-magic~=0.4.27
Requires-Dist: tqdm~=4.67.0
